bids_manager/__init__.py
bids_manager/build_heuristic_from_tsv.py
bids_manager/dicom_inventory.py
bids_manager/fill_bids_ignore.py
bids_manager/gui.py
bids_manager/post_conv_renamer.py
bids_manager/run_heudiconv_from_heuristic.py
bids_manager/scans_utils.py
bids_manager/schema_renamer.py
bids_manager/miscellaneous/images/ANCP_lab.png
bids_manager/miscellaneous/images/Icon.png
bids_manager/miscellaneous/images/Jochem.jpg
bids_manager/miscellaneous/images/Karel.jpeg
bids_manager/miscellaneous/images/Logo.png
bids_manager-0.2.4.dist-info/licenses/LICENSE
bids_manager-0.2.4.dist-info/METADATA
bids_manager-0.2.4.dist-info/WHEEL
bids_manager-0.2.4.dist-info/entry_points.txt
bids_manager-0.2.4.dist-info/top_level.txt
bids_manager-0.2.4.dist-info/RECORD
